cnn-design/accelerator-design/codes/verilog/shifter.v
module shifter
	#(
	parameter IN_WIDTH		= 20,
	parameter SHFT_WIDTH	= 4,
	parameter OUT_WIDTH		= 20
	)
	(
	input			[IN_WIDTH-1:0] 					in,
	input			[SHFT_WIDTH-1:0] 				shift, // value 0
	output	reg		[OUT_WIDTH-1:0]					out
    );

	always@*
		case (shift)
		00:	out	= in[IN_WIDTH-1-00: IN_WIDTH-OUT_WIDTH-00];
		01:	out	= in[IN_WIDTH-1-01: IN_WIDTH-OUT_WIDTH-01];
		02:	out	= in[IN_WIDTH-1-02: IN_WIDTH-OUT_WIDTH-02];
		03:	out	= in[IN_WIDTH-1-03: IN_WIDTH-OUT_WIDTH-03];
		04:	out	= in[IN_WIDTH-1-04: IN_WIDTH-OUT_WIDTH-04];
		05:	out	= in[IN_WIDTH-1-05: IN_WIDTH-OUT_WIDTH-05];
		06:	out	= in[IN_WIDTH-1-06: IN_WIDTH-OUT_WIDTH-06];
		07:	out	= in[IN_WIDTH-1-07: IN_WIDTH-OUT_WIDTH-07];
		08:	out	= in[IN_WIDTH-1-08: IN_WIDTH-OUT_WIDTH-08];
		09:	out	= in[IN_WIDTH-1-09: IN_WIDTH-OUT_WIDTH-09];
		10:	out	= in[IN_WIDTH-1-10: IN_WIDTH-OUT_WIDTH-10];
		11:	out	= in[IN_WIDTH-1-11: IN_WIDTH-OUT_WIDTH-11];
		12:	out	= in[IN_WIDTH-1-12: IN_WIDTH-OUT_WIDTH-12];
		endcase
endmodule

cnn-design/accelerator-design/codes/simulations/tb_shifter.v
`include "../verilog/shifter.v"

module tb_shifter;
	
	parameter IN_WIDTH		= 20;
	parameter SHFT_WIDTH	= 4;
	parameter OUT_WIDTH		= 20;

	reg	 [IN_WIDTH-1:0] in;
	reg	 [SHFT_WIDTH-1:0] shift;
	wire [OUT_WIDTH-1:0] out;

	integer i;

	shifter
	# (
		.IN_WIDTH (20),
		.SHFT_WIDTH (4),
		.OUT_WIDTH (20)
	)
	shifter_inst
	(
		.in (in),
		.shift (shift),
		.out (out)
	);
	
	initial
	begin
		$dumpfile("shifter.vcd");
		$dumpvars(1, tb_shifter);
		
		in		= 0;
		shift	= 0;
		i       = 0;

		#1
		for ( i = 0; i < 5; i = i + 1)
			begin
			#2
			in = 20'b0000_0000_0000_0000_0000 + i;
			$display("in = %20b", shifter_inst.in);
			#2
			$display("ou = %20b\nshift was %4b\n", out, shift);  
			end
		
		$finish;
	end

endmodule

cnn-design/accelerator-design/codes/simulations/shifter.vcd
$date
	Fri Mar  8 13:43:42 2024
$end
$version
	Icarus Verilog
$end
$timescale
	1s
$end
$scope module tb_shifter $end
$var wire 20 ! out [19:0] $end
$var parameter 32 " IN_WIDTH $end
$var parameter 32 # OUT_WIDTH $end
$var parameter 32 $ SHFT_WIDTH $end
$var reg 20 % in [19:0] $end
$var reg 4 & shift [3:0] $end
$var integer 32 ' i [31:0] $end
$upscope $end
$enddefinitions $end
$comment Show the parameter values. $end
$dumpall
b100 $
b10100 #
b10100 "
$end
#0
$dumpvars
b0 '
b0 &
b0 %
b0 !
$end
#5
b1 '
#7
b1 !
b1 %
#9
b10 '
#11
b10 !
b10 %
#13
b11 '
#15
b11 !
b11 %
#17
b100 '
#19
b100 !
b100 %
#21
b101 '
