cnn-design/accelerator-design/codes/verilog/max_pool.v
module max_pool
	#(
		parameter DWIDTH = 20
	)
	(
	input						clk,
	input						reset,
	input						en_maxpool,
	input		[DWIDTH-1:0]	data_in,
	input						valid_in,
	
	output reg	[DWIDTH-1:0]	data_out,
	output reg					valid_out
	);

	reg	[DWIDTH-1:0]	data_r;
	reg	[DWIDTH-1:0]	data_r_r;
	reg	[DWIDTH-1:0]	max_pool_out;
	reg					max_pool_valid;

	always@(posedge clk)
		if(reset)			data_r		<= 0;
		else if(valid_in)	data_r		<= data_in;

	always@* max_pool_out <= (data_r > data_in) ? data_r: data_in;
	

	reg toggle;	
	always@(posedge clk)
		if		(reset | ~en_maxpool)	toggle <= 0;
		else if (valid_in)				toggle <= ~toggle;
	
	always@* max_pool_valid <= toggle & valid_in;

	always@(posedge clk) 
		if(reset)	
		begin
			data_out 	<= 0;
		    valid_out	<= 0;
		end
		else
		begin
			data_out 	<= en_maxpool ? max_pool_out	: data_in;
		    valid_out	<= en_maxpool ? max_pool_valid	: valid_in;
		end

endmodule

cnn-design/accelerator-design/codes/simulations/tb_maxpool.v
`include "../verilog/max_pool.v"

module tb_maxpool;
	parameter DWIDTH = 20;
	reg						clk;
	reg						reset;
	reg						en_maxpool;
	reg		[DWIDTH-1:0]	data_in;
	reg						valid_in;
	
	wire 	[DWIDTH-1:0]	data_out;
	wire					valid_out;
	integer					i;
	max_pool
	#(
		.DWIDTH 	(20 		)
	)
	max_pool_inst
	(
	.clk			(clk		),
	.reset			(reset		),
	.en_maxpool		(en_maxpool	),
	.data_in		(data_in	),
	.valid_in		(valid_in	),
	.data_out		(data_out	),
	.valid_out		(valid_out	)
	);
	
	initial
	begin
		clk = 0;
		forever #5 clk = ~clk;
	end

	initial
	begin
		$dumpfile("wave_mp.vcd");
		$dumpvars(0, tb_maxpool);
		
		reset		= 0;
		en_maxpool	= 0;
		data_in		= 0;
		valid_in	= 0;

		repeat(2) @(posedge clk);
		#1 reset		= 1;

		repeat(2) @(posedge clk);
		#1 reset		= 0;
		
		repeat(10) @(posedge clk);
		
		#1 valid_in = 1;

		@(posedge clk);
		$display("\ninitial in = %10d\nou = %10d\n", data_in, data_out);


		for(i = 1; i < 5; i = i + 1)
		begin
			@(posedge clk);
			#1 data_in = i;
			@(posedge clk);
			@(posedge clk);
			$display("\nin = %10d\nou = %10d\n", data_in, data_out);
		end
		#1 valid_in = 0;
					
		repeat(10) @(posedge clk);
		#1 valid_in = 1;
		data_in		= 0;
		en_maxpool	= 1;
		for(i=1; i <20; i=i+1)
		begin
			@(posedge clk);
			#1 data_in = i;
		end
		
		$finish;
	end

endmodule

cnn-design/accelerator-design/codes/simulations/wave_mp.vcd
$date
	Fri Mar  8 16:34:41 2024
$end
$version
	Icarus Verilog
$end
$timescale
	1s
$end
$scope module tb_maxpool $end
$var wire 1 ! valid_out $end
$var wire 20 " data_out [19:0] $end
$var parameter 32 # DWIDTH $end
$var reg 1 $ clk $end
$var reg 20 % data_in [19:0] $end
$var reg 1 & en_maxpool $end
$var reg 1 ' reset $end
$var reg 1 ( valid_in $end
$var integer 32 ) i [31:0] $end
$scope module max_pool_inst $end
$var wire 1 $ clk $end
$var wire 20 * data_in [19:0] $end
$var wire 1 & en_maxpool $end
$var wire 1 ' reset $end
$var wire 1 ( valid_in $end
$var parameter 32 + DWIDTH $end
$var reg 20 , data_out [19:0] $end
$var reg 20 - data_r [19:0] $end
$var reg 20 . max_pool_out [19:0] $end
$var reg 1 / max_pool_valid $end
$var reg 1 0 toggle $end
$var reg 1 ! valid_out $end
$upscope $end
$upscope $end
$enddefinitions $end
$comment Show the parameter values. $end
$dumpall
b10100 +
b10100 #
$end
#0
$dumpvars
x0
0/
bx .
bx -
bx ,
b0 *
bx )
0(
0'
0&
b0 %
0$
bx "
x!
$end
#5
00
0!
b0 "
b0 ,
1$
#10
0$
#15
1$
#16
1'
#20
0$
#25
b0 .
b0 -
1$
#30
0$
#35
1$
#36
0'
#40
0$
#45
1$
#50
0$
#55
1$
#60
0$
#65
1$
#70
0$
#75
1$
#80
0$
#85
1$
#90
0$
#95
1$
#100
0$
#105
1$
#110
0$
#115
1$
#120
0$
#125
1$
#130
0$
#135
1$
#136
1(
#140
0$
#145
1!
b1 )
1$
#150
0$
#155
1$
#156
b1 .
b1 %
b1 *
#160
0$
#165
b1 -
b1 "
b1 ,
1$
#170
0$
#175
b10 )
1$
#180
0$
#185
1$
#186
b10 .
b10 %
b10 *
#190
0$
#195
b10 "
b10 ,
b10 -
1$
#200
0$
#205
b11 )
1$
#210
0$
#215
1$
#216
b11 .
b11 %
b11 *
#220
0$
#225
b11 -
b11 "
b11 ,
1$
#230
0$
#235
b100 )
1$
#240
0$
#245
1$
#246
b100 .
b100 %
b100 *
#250
0$
#255
b100 "
b100 ,
b100 -
1$
#260
0$
#265
b101 )
1$
#266
0(
#270
0$
#275
0!
1$
#280
0$
#285
1$
#290
0$
#295
1$
#300
0$
#305
1$
#310
0$
#315
1$
#320
0$
#325
1$
#330
0$
#335
1$
#340
0$
#345
1$
#350
0$
#355
1$
#360
0$
#365
1$
#366
b1 )
1&
b0 %
b0 *
1(
#370
0$
#375
1/
b0 .
10
b0 -
1$
#376
b1 .
b10 )
b1 %
b1 *
#380
0$
#385
0/
b1 -
00
1!
b1 "
b1 ,
1$
#386
b10 .
b11 )
b10 %
b10 *
#390
0$
#395
1/
0!
b10 "
b10 ,
10
b10 -
1$
#396
b11 .
b100 )
b11 %
b11 *
#400
0$
#405
0/
b11 -
00
1!
b11 "
b11 ,
1$
#406
b100 .
b101 )
b100 %
b100 *
#410
0$
#415
1/
0!
b100 "
b100 ,
10
b100 -
1$
#416
b101 .
b110 )
b101 %
b101 *
#420
0$
#425
0/
b101 -
00
1!
b101 "
b101 ,
1$
#426
b110 .
b111 )
b110 %
b110 *
#430
0$
#435
1/
0!
b110 "
b110 ,
10
b110 -
1$
#436
b111 .
b1000 )
b111 %
b111 *
#440
0$
#445
0/
b111 -
00
1!
b111 "
b111 ,
1$
#446
b1000 .
b1001 )
b1000 %
b1000 *
#450
0$
#455
1/
0!
b1000 "
b1000 ,
10
b1000 -
1$
#456
b1001 .
b1010 )
b1001 %
b1001 *
#460
0$
#465
0/
b1001 -
00
1!
b1001 "
b1001 ,
1$
#466
b1010 .
b1011 )
b1010 %
b1010 *
#470
0$
#475
1/
0!
b1010 "
b1010 ,
10
b1010 -
1$
#476
b1011 .
b1100 )
b1011 %
b1011 *
#480
0$
#485
0/
b1011 -
00
1!
b1011 "
b1011 ,
1$
#486
b1100 .
b1101 )
b1100 %
b1100 *
#490
0$
#495
1/
0!
b1100 "
b1100 ,
10
b1100 -
1$
#496
b1101 .
b1110 )
b1101 %
b1101 *
#500
0$
#505
0/
b1101 -
00
1!
b1101 "
b1101 ,
1$
#506
b1110 .
b1111 )
b1110 %
b1110 *
#510
0$
#515
1/
0!
b1110 "
b1110 ,
10
b1110 -
1$
#516
b1111 .
b10000 )
b1111 %
b1111 *
#520
0$
#525
0/
b1111 -
00
1!
b1111 "
b1111 ,
1$
#526
b10000 .
b10001 )
b10000 %
b10000 *
#530
0$
#535
1/
0!
b10000 "
b10000 ,
10
b10000 -
1$
#536
b10001 .
b10010 )
b10001 %
b10001 *
#540
0$
#545
0/
b10001 -
00
1!
b10001 "
b10001 ,
1$
#546
b10010 .
b10011 )
b10010 %
b10010 *
#550
0$
#555
1/
0!
b10010 "
b10010 ,
10
b10010 -
1$
#556
b10011 .
b10100 )
b10011 %
b10011 *
